supply/__init__.py
supply-0.0.1.dist-info/LICENSE
supply-0.0.1.dist-info/METADATA
supply-0.0.1.dist-info/WHEEL
supply-0.0.1.dist-info/top_level.txt
supply-0.0.1.dist-info/RECORD
